{"type": "setlists", "itemsPerPage": 20, "page": 15, "total": 462, "setlist": [{"id": "3dae153", "versionId": "1bf0b1b8", "eventDate": "31-05-2012", "lastUpdated": "2012-11-20T07:13:11.000+0000", "artist": {"mbid": "b2e2abfa-fb1e-4be0-b500-56c4584f41cd", "name": "Railroad Earth", "sortName": "Railroad Earth", "disambiguation": "", "url": "https://www.setlist.fm/setlists/railroad-earth-2bd6d8c2.html"}, "venue": {"id": "6bd66662", "name": "Mulberry Mountain", "city": {"id": "4125181", "name": "Ozark", "state": "Arkansas", "stateCode": "AR", "coords": {"lat": 35.4870295, "long": -93.8276965}, "country": {"code": "US", "name": "United States"}}, "url": "https://www.setlist.fm/venue/mulberry-mountain-ozark-ar-usa-6bd66662.html"}, "sets": {"set": []}, "url": "https://www.setlist.fm/setlist/railroad-earth/2012/mulberry-mountain-ozark-ar-3dae153.html"}, {"id": "23c6fce7", "versionId": "4bb63792", "eventDate": "19-05-2012", "lastUpdated": "2015-06-16T21:11:28.000+0000", "artist": {"mbid": "b2e2abfa-fb1e-4be0-b500-56c4584f41cd", "name": "Railroad Earth", "sortName": "Railroad Earth", "disambiguation": "", "url": "https://www.setlist.fm/setlists/railroad-earth-2bd6d8c2.html"}, "venue": {"id": "1bd5ada4", "name": "", "city": {"id": "5141653", "name": "Tuxedo Park", "state": "New York", "stateCode": "NY", "coords": {"lat": 41.1934278, "long": -74.1843129}, "country": {"code": "US", "name": "United States"}}, "url": "https://www.setlist.fm/venue/unknown-venue-tuxedo-park-ny-usa-1bd5ada4.html"}, "sets": {"set": []}, "url": "https://www.setlist.fm/setlist/railroad-earth/2012/unknown-venue-tuxedo-park-ny-23c6fce7.html"}, {"id": "53d90b45", "versionId": "232b70b7", "eventDate": "18-05-2012", "lastUpdated": "2020-10-30T10:22:15.000+0000", "artist": {"mbid": "b2e2abfa-fb1e-4be0-b500-56c4584f41cd", "name": "Railroad Earth", "sortName": "Railroad Earth", "disambiguation": "", "url": "https://www.setlist.fm/setlists/railroad-earth-2bd6d8c2.html"}, "venue": {"id": "1bd5ada4", "name": "", "city": {"id": "5141653", "name": "Tuxedo Park", "state": "New York", "stateCode": "NY", "coords": {"lat": 41.1934278, "long": -74.1843129}, "country": {"code": "US", "name": "United States"}}, "url": "https://www.setlist.fm/venue/unknown-venue-tuxedo-park-ny-usa-1bd5ada4.html"}, "sets": {"set": [{"name": "Set 1:", "song": [{"name": "Mourning Flies"}, {"name": "Lone Croft Farewell"}, {"name": "Bread and Water"}, {"name": "Just So You Know"}, {"name": "Came Up Smilin'"}, {"name": "Dandelion Wine"}, {"name": "Seven Story Mountain"}]}, {"name": "Set 2:", "song": [{"name": "1759"}, {"name": "Where Songs Begin"}, {"name": "Long Way to Go"}, {"name": "Chains"}, {"name": "Daddy-O"}, {"name": "Black Elk Speaks"}, {"name": "Black Bear"}, {"name": "The Jupiter & the 119"}, {"name": "Happy Song"}, {"name": "Bird in a House"}]}, {"encore": 1, "song": [{"name": "Reuben's Train", "cover": {"mbid": "9be7f096-97ec-4615-8957-8d40b5dcbc41", "name": "[traditional]", "sortName": "[traditional]", "disambiguation": "Special Purpose Artist", "url": "https://www.setlist.fm/setlists/traditional-5bd2f7e4.html"}}]}]}, "url": "https://www.setlist.fm/setlist/railroad-earth/2012/unknown-venue-tuxedo-park-ny-53d90b45.html"}, {"id": "6b980e2a", "versionId": "2335d02b", "eventDate": "13-04-2012", "lastUpdated": "2020-02-15T14:04:11.000+0000", "artist": {"mbid": "b2e2abfa-fb1e-4be0-b500-56c4584f41cd", "name": "Railroad Earth", "sortName": "Railroad Earth", "disambiguation": "", "url": "https://www.setlist.fm/setlists/railroad-earth-2bd6d8c2.html"}, "venue": {"id": "63d3a697", "name": "World Caf\u00e9 Live Downstairs", "city": {"id": "4560349", "name": "Philadelphia", "state": "Pennsylvania", "stateCode": "PA", "coords": {"lat": 39.952335, "long": -75.163789}, "country": {"code": "US", "name": "United States"}}, "url": "https://www.setlist.fm/venue/world-cafe-live-downstairs-philadelphia-pa-usa-63d3a697.html"}, "sets": {"set": []}, "url": "https://www.setlist.fm/setlist/railroad-earth/2012/world-cafe-live-downstairs-philadelphia-pa-6b980e2a.html"}, {"id": "bdecd12", "versionId": "537caf99", "eventDate": "10-03-2012", "lastUpdated": "2018-06-03T18:59:37.000+0000", "artist": {"mbid": "b2e2abfa-fb1e-4be0-b500-56c4584f41cd", "name": "Railroad Earth", "sortName": "Railroad Earth", "disambiguation": "", "url": "https://www.setlist.fm/setlists/railroad-earth-2bd6d8c2.html"}, "venue": {"id": "3d23db7", "name": "The Fillmore", "city": {"id": "5391959", "name": "San Francisco", "state": "California", "stateCode": "CA", "coords": {"lat": 37.775, "long": -122.419}, "country": {"code": "US", "name": "United States"}}, "url": "https://www.setlist.fm/venue/the-fillmore-san-francisco-ca-usa-3d23db7.html"}, "sets": {"set": [{"name": "Set One", "song": [{"name": "Bird in a House"}, {"name": "Happy Song"}, {"name": "Elko"}, {"name": "Storms"}, {"name": "Stillwater Getaway"}, {"name": "Mourning Flies"}, {"name": "Lone Croft Farewell"}]}, {"name": "Set Two", "song": [{"name": "Mighty River"}, {"name": "Warhead Boogie"}, {"name": "Congoman Chant"}, {"name": "Terrapin Station", "cover": {"mbid": "6faa7ca7-0d99-4a5e-bfa6-1fd5037520c6", "name": "Grateful Dead", "sortName": "Grateful Dead", "disambiguation": "", "url": "https://www.setlist.fm/setlists/grateful-dead-bd6ad4a.html"}, "info": "with Phil Lesh"}, {"name": "Spring-Heeled Jack", "info": "with Phil Lesh"}, {"name": "Crazy Fingers", "cover": {"mbid": "6faa7ca7-0d99-4a5e-bfa6-1fd5037520c6", "name": "Grateful Dead", "sortName": "Grateful Dead", "disambiguation": "", "url": "https://www.setlist.fm/setlists/grateful-dead-bd6ad4a.html"}, "info": "with Phil Lesh"}, {"name": "Box of Rain", "cover": {"mbid": "6faa7ca7-0d99-4a5e-bfa6-1fd5037520c6", "name": "Grateful Dead", "sortName": "Grateful Dead", "disambiguation": "", "url": "https://www.setlist.fm/setlists/grateful-dead-bd6ad4a.html"}, "info": "with Phil Lesh"}, {"name": "Peace on Earth"}]}, {"name": "Encore", "song": [{"name": "Cuckoo's Medley"}]}]}, "url": "https://www.setlist.fm/setlist/railroad-earth/2012/the-fillmore-san-francisco-ca-bdecd12.html"}, {"id": "43f8a3c3", "versionId": "2b2d6cf2", "eventDate": "09-03-2012", "lastUpdated": "2020-10-29T07:11:30.000+0000", "artist": {"mbid": "b2e2abfa-fb1e-4be0-b500-56c4584f41cd", "name": "Railroad Earth", "sortName": "Railroad Earth", "disambiguation": "", "url": "https://www.setlist.fm/setlists/railroad-earth-2bd6d8c2.html"}, "venue": {"id": "3d23db7", "name": "The Fillmore", "city": {"id": "5391959", "name": "San Francisco", "state": "California", "stateCode": "CA", "coords": {"lat": 37.775, "long": -122.419}, "country": {"code": "US", "name": "United States"}}, "url": "https://www.setlist.fm/venue/the-fillmore-san-francisco-ca-usa-3d23db7.html"}, "sets": {"set": [{"name": "Set 1:", "song": [{"name": "Saddle of the Sun"}, {"name": "Like a Buddha"}, {"name": "Give That Boy a Hand"}, {"name": "For Love", "cover": {"mbid": "c81d48a8-5c86-4160-b3d4-1275e7ba3212", "name": "Robert Earl Keen", "sortName": "Keen, Robert Earl", "disambiguation": "", "url": "https://www.setlist.fm/setlists/robert-earl-keen-2bd6287e.html"}}, {"name": "Bread and Water"}, {"name": "The Hunting Song"}, {"name": "Mission Man"}, {"name": "Long Way to Go"}]}, {"name": "Set 2:", "song": [{"name": "Black Elk Speaks"}, {"name": "Birds of America"}, {"name": "Gold Rush"}, {"name": "Cold Water", "cover": {"mbid": "c3aeb863-7b26-4388-94e8-5a240f2be21b", "name": "Tom Waits", "sortName": "Waits, Tom", "disambiguation": "", "url": "https://www.setlist.fm/setlists/tom-waits-3bd6c0ac.html"}}, {"name": "You Never Know"}, {"name": "Potter's Field"}, {"name": "1759"}, {"name": "Dover to Dunkirk"}, {"name": "Seven Story Mountain"}, {"name": "Hard Livin'"}]}, {"encore": 1, "song": [{"name": "Dance Around Molly", "cover": {"mbid": "9be7f096-97ec-4615-8957-8d40b5dcbc41", "name": "[traditional]", "sortName": "[traditional]", "disambiguation": "Special Purpose Artist", "url": "https://www.setlist.fm/setlists/traditional-5bd2f7e4.html"}}, {"name": "Dandelion Wine"}]}]}, "url": "https://www.setlist.fm/setlist/railroad-earth/2012/the-fillmore-san-francisco-ca-43f8a3c3.html"}, {"id": "33d804e5", "versionId": "7bfa0a94", "eventDate": "09-03-2012", "lastUpdated": "2013-05-04T16:50:57.000+0000", "artist": {"mbid": "b2e2abfa-fb1e-4be0-b500-56c4584f41cd", "name": "Railroad Earth", "sortName": "Railroad Earth", "disambiguation": "", "url": "https://www.setlist.fm/setlists/railroad-earth-2bd6d8c2.html"}, "venue": {"id": "6bd6461a", "name": "Best Buy Theater", "city": {"id": "5128581", "name": "New York", "state": "New York", "stateCode": "NY", "coords": {"lat": 40.7142691, "long": -74.0059729}, "country": {"code": "US", "name": "United States"}}, "url": "https://www.setlist.fm/venue/best-buy-theater-new-york-ny-usa-6bd6461a.html"}, "sets": {"set": []}, "url": "https://www.setlist.fm/setlist/railroad-earth/2012/best-buy-theater-new-york-ny-33d804e5.html"}, {"id": "43dc5783", "versionId": "3f7115f", "eventDate": "25-02-2012", "lastUpdated": "2012-09-02T14:37:22.000+0000", "artist": {"mbid": "b2e2abfa-fb1e-4be0-b500-56c4584f41cd", "name": "Railroad Earth", "sortName": "Railroad Earth", "disambiguation": "", "url": "https://www.setlist.fm/setlists/railroad-earth-2bd6d8c2.html"}, "venue": {"id": "6bd6461a", "name": "Best Buy Theater", "city": {"id": "5128581", "name": "New York", "state": "New York", "stateCode": "NY", "coords": {"lat": 40.7142691, "long": -74.0059729}, "country": {"code": "US", "name": "United States"}}, "url": "https://www.setlist.fm/venue/best-buy-theater-new-york-ny-usa-6bd6461a.html"}, "sets": {"set": []}, "url": "https://www.setlist.fm/setlist/railroad-earth/2012/best-buy-theater-new-york-ny-43dc5783.html"}, {"id": "439fbbff", "versionId": "304098f", "eventDate": "24-02-2012", "lastUpdated": "2019-08-04T07:44:06.000+0000", "artist": {"mbid": "b2e2abfa-fb1e-4be0-b500-56c4584f41cd", "name": "Railroad Earth", "sortName": "Railroad Earth", "disambiguation": "", "url": "https://www.setlist.fm/setlists/railroad-earth-2bd6d8c2.html"}, "venue": {"id": "43d61f2f", "name": "Paradise Rock Club", "city": {"id": "4930956", "name": "Boston", "state": "Massachusetts", "stateCode": "MA", "coords": {"lat": 42.3584308, "long": -71.0597732}, "country": {"code": "US", "name": "United States"}}, "url": "https://www.setlist.fm/venue/paradise-rock-club-boston-ma-usa-43d61f2f.html"}, "sets": {"set": []}, "url": "https://www.setlist.fm/setlist/railroad-earth/2012/paradise-rock-club-boston-ma-439fbbff.html"}, {"id": "13949d21", "versionId": "6b6aaa22", "eventDate": "03-02-2012", "lastUpdated": "2018-12-11T20:16:30.000+0000", "artist": {"mbid": "b2e2abfa-fb1e-4be0-b500-56c4584f41cd", "name": "Railroad Earth", "sortName": "Railroad Earth", "disambiguation": "", "url": "https://www.setlist.fm/setlists/railroad-earth-2bd6d8c2.html"}, "venue": {"id": "3d63d9f", "name": "The Orange Peel", "city": {"id": "4453066", "name": "Asheville", "state": "North Carolina", "stateCode": "NC", "coords": {"lat": 35.6009452, "long": -82.554015}, "country": {"code": "US", "name": "United States"}}, "url": "https://www.setlist.fm/venue/the-orange-peel-asheville-nc-usa-3d63d9f.html"}, "sets": {"set": []}, "url": "https://www.setlist.fm/setlist/railroad-earth/2012/the-orange-peel-asheville-nc-13949d21.html"}, {"id": "bdebd1a", "versionId": "bc17d9e", "eventDate": "29-01-2012", "lastUpdated": "2012-01-29T16:15:48.000+0000", "artist": {"mbid": "b2e2abfa-fb1e-4be0-b500-56c4584f41cd", "name": "Railroad Earth", "sortName": "Railroad Earth", "disambiguation": "", "url": "https://www.setlist.fm/setlists/railroad-earth-2bd6d8c2.html"}, "venue": {"id": "5bd7c770", "name": "Super Bowl Village", "city": {"id": "4259418", "name": "Indianapolis", "state": "Indiana", "stateCode": "IN", "coords": {"lat": 39.7683765, "long": -86.1580423}, "country": {"code": "US", "name": "United States"}}, "url": "https://www.setlist.fm/venue/super-bowl-village-indianapolis-in-usa-5bd7c770.html"}, "sets": {"set": []}, "url": "https://www.setlist.fm/setlist/railroad-earth/2012/super-bowl-village-indianapolis-in-bdebd1a.html"}, {"id": "1be91508", "versionId": "7b624254", "eventDate": "28-01-2012", "lastUpdated": "2018-09-29T03:45:41.000+0000", "artist": {"mbid": "b2e2abfa-fb1e-4be0-b500-56c4584f41cd", "name": "Railroad Earth", "sortName": "Railroad Earth", "disambiguation": "", "url": "https://www.setlist.fm/setlists/railroad-earth-2bd6d8c2.html"}, "venue": {"id": "23d6206b", "name": "House of Blues", "city": {"id": "4887398", "name": "Chicago", "state": "Illinois", "stateCode": "IL", "coords": {"lat": 41.850033, "long": -87.6500523}, "country": {"code": "US", "name": "United States"}}, "url": "https://www.setlist.fm/venue/house-of-blues-chicago-il-usa-23d6206b.html"}, "sets": {"set": []}, "url": "https://www.setlist.fm/setlist/railroad-earth/2012/house-of-blues-chicago-il-1be91508.html"}, {"id": "1bfe35b0", "versionId": "63a8e6f7", "eventDate": "21-01-2012", "lastUpdated": "2016-09-23T16:11:55.000+0000", "artist": {"mbid": "b2e2abfa-fb1e-4be0-b500-56c4584f41cd", "name": "Railroad Earth", "sortName": "Railroad Earth", "disambiguation": "", "url": "https://www.setlist.fm/setlists/railroad-earth-2bd6d8c2.html"}, "venue": {"id": "1bd7e1a8", "name": "The Jefferson Theater", "city": {"id": "4752031", "name": "Charlottesville", "state": "Virginia", "stateCode": "VA", "coords": {"lat": 38.0293059, "long": -78.4766781}, "country": {"code": "US", "name": "United States"}}, "url": "https://www.setlist.fm/venue/the-jefferson-theater-charlottesville-va-usa-1bd7e1a8.html"}, "sets": {"set": []}, "url": "https://www.setlist.fm/setlist/railroad-earth/2012/the-jefferson-theater-charlottesville-va-1bfe35b0.html"}, {"id": "3fe35ab", "versionId": "53a133d9", "eventDate": "20-01-2012", "lastUpdated": "2016-06-04T21:28:28.000+0000", "artist": {"mbid": "b2e2abfa-fb1e-4be0-b500-56c4584f41cd", "name": "Railroad Earth", "sortName": "Railroad Earth", "disambiguation": "", "url": "https://www.setlist.fm/setlists/railroad-earth-2bd6d8c2.html"}, "venue": {"id": "1bd7e1a8", "name": "The Jefferson Theater", "city": {"id": "4752031", "name": "Charlottesville", "state": "Virginia", "stateCode": "VA", "coords": {"lat": 38.0293059, "long": -78.4766781}, "country": {"code": "US", "name": "United States"}}, "url": "https://www.setlist.fm/venue/the-jefferson-theater-charlottesville-va-usa-1bd7e1a8.html"}, "sets": {"set": []}, "url": "https://www.setlist.fm/setlist/railroad-earth/2012/the-jefferson-theater-charlottesville-va-3fe35ab.html"}, {"id": "63de529b", "versionId": "1b2be97c", "eventDate": "30-12-2011", "lastUpdated": "2020-10-30T09:30:32.000+0000", "artist": {"mbid": "b2e2abfa-fb1e-4be0-b500-56c4584f41cd", "name": "Railroad Earth", "sortName": "Railroad Earth", "disambiguation": "", "url": "https://www.setlist.fm/setlists/railroad-earth-2bd6d8c2.html"}, "venue": {"id": "6bd63666", "name": "Ogden Theatre", "city": {"id": "5419384", "name": "Denver", "state": "Colorado", "stateCode": "CO", "coords": {"lat": 39.7391536, "long": -104.9847034}, "country": {"code": "US", "name": "United States"}}, "url": "https://www.setlist.fm/venue/ogden-theatre-denver-co-usa-6bd63666.html"}, "sets": {"set": [{"name": "Set 1", "song": [{"name": "Walk Beside Me", "cover": {"mbid": "07194211-0eda-43c4-8d04-0dbbc1f89674", "name": "Tim O\u2019Brien & Darrell Scott", "sortName": "O\u2019Brien, Tim & Scott, Darrell", "url": "https://www.setlist.fm/setlists/tim-obrien-and-darrell-scott-5bdae39c.html"}}, {"name": "Lordy Lordy"}, {"name": "Bread and Water"}, {"name": "Little Bit o' Me"}, {"name": "Stillwater Getaway"}, {"name": "The Hunting Song", "info": "Kyle Hollingsworth, keys for remainder of the show"}, {"name": "Mourning Flies"}, {"name": "Said What You Mean"}, {"name": "Long Way to Go"}]}, {"name": "Set 2", "song": [{"name": "Old Man and the Land"}, {"name": "Head", "info": ">"}, {"name": "Will It Go Round in Circles", "cover": {"mbid": "8a7cf497-dc5c-4523-932d-3fcbc9a69d38", "name": "Billy Preston", "sortName": "Preston, Billy", "disambiguation": "", "url": "https://www.setlist.fm/setlists/billy-preston-4bd69792.html"}}, {"name": "Bringin' My Baby Back Home"}, {"name": "The Forecast", "info": ">"}, {"name": "The Man Who Invented Sin", "info": ">"}, {"name": "Mighty River", "info": ">"}, {"name": "Like a Buddha"}, {"name": "Elko"}]}, {"encore": 1, "song": [{"name": "I've Just Seen a Face", "cover": {"mbid": "b10bbbfc-cf9e-42e0-be17-e2c3e1d2600d", "name": "The Beatles", "sortName": "Beatles, The", "disambiguation": "", "url": "https://www.setlist.fm/setlists/the-beatles-23d6a88b.html"}}, {"name": "Bird in a House"}]}]}, "url": "https://www.setlist.fm/setlist/railroad-earth/2011/ogden-theatre-denver-co-63de529b.html"}, {"id": "63d90ebb", "versionId": "3b2d5ca4", "eventDate": "26-11-2011", "lastUpdated": "2020-10-29T07:17:46.000+0000", "artist": {"mbid": "b2e2abfa-fb1e-4be0-b500-56c4584f41cd", "name": "Railroad Earth", "sortName": "Railroad Earth", "disambiguation": "", "url": "https://www.setlist.fm/setlists/railroad-earth-2bd6d8c2.html"}, "venue": {"id": "4bd6731a", "name": "Sherman Theater", "city": {"id": "5214543", "name": "Stroudsburg", "state": "Pennsylvania", "stateCode": "PA", "coords": {"lat": 40.9867609, "long": -75.1946248}, "country": {"code": "US", "name": "United States"}}, "url": "https://www.setlist.fm/venue/sherman-theater-stroudsburg-pa-usa-4bd6731a.html"}, "sets": {"set": [{"name": "Set One", "song": [{"name": "The Forecast"}, {"name": "Mighty River"}, {"name": "Shockenaw Mountain Breakdown"}, {"name": "The Jupiter & the 119"}, {"name": "The Good Life"}, {"name": "Elko"}, {"name": "El Cumbanchero"}, {"name": "Everything Comes Together"}]}, {"name": "Set Two", "song": [{"name": "Right in Tune"}, {"name": "Green Roofs of Eiream"}, {"name": "Like a Buddha"}, {"name": "Give That Boy a Hand"}, {"name": "Genesis"}, {"name": "Potter's Field"}, {"name": "Lone Croft Farewell"}, {"name": "The Man Who Invented Sin"}, {"name": "Warhead Boogie"}, {"name": "Way of the Buffalo"}, {"name": "The Wheel", "cover": {"mbid": "1ecff755-607d-4130-9a8a-8873f27e5de5", "name": "Jerry Garcia", "sortName": "Garcia, Jerry", "disambiguation": "", "url": "https://www.setlist.fm/setlists/jerry-garcia-bd6adce.html"}}, {"name": "Hard Livin'"}]}, {"encore": 1, "song": [{"name": "Happy Song"}]}]}, "url": "https://www.setlist.fm/setlist/railroad-earth/2011/sherman-theater-stroudsburg-pa-63d90ebb.html"}, {"id": "73d90ec1", "versionId": "332b5069", "eventDate": "25-11-2011", "lastUpdated": "2020-10-30T10:35:02.000+0000", "artist": {"mbid": "b2e2abfa-fb1e-4be0-b500-56c4584f41cd", "name": "Railroad Earth", "sortName": "Railroad Earth", "disambiguation": "", "url": "https://www.setlist.fm/setlists/railroad-earth-2bd6d8c2.html"}, "venue": {"id": "4bd6731a", "name": "Sherman Theater", "city": {"id": "5214543", "name": "Stroudsburg", "state": "Pennsylvania", "stateCode": "PA", "coords": {"lat": 40.9867609, "long": -75.1946248}, "country": {"code": "US", "name": "United States"}}, "url": "https://www.setlist.fm/venue/sherman-theater-stroudsburg-pa-usa-4bd6731a.html"}, "sets": {"set": [{"name": "Set One", "song": [{"name": "Lordy Lordy"}, {"name": "The Hunting Song"}, {"name": "Drag Him Down"}, {"name": "The Cuckoo", "cover": {"mbid": "9be7f096-97ec-4615-8957-8d40b5dcbc41", "name": "[traditional]", "sortName": "[traditional]", "disambiguation": "Special Purpose Artist", "url": "https://www.setlist.fm/setlists/traditional-5bd2f7e4.html"}}, {"name": "Real Love"}, {"name": "Mourning Flies"}, {"name": "Just So You Know"}, {"name": "Gold Rush"}, {"name": "Wavin' Willie"}]}, {"name": "Set Two", "song": [{"name": "Where Songs Begin"}, {"name": "Head"}, {"name": "Storms"}, {"name": "Seven Story Mountain"}, {"name": "Dance Around Molly", "cover": {"mbid": "9be7f096-97ec-4615-8957-8d40b5dcbc41", "name": "[traditional]", "sortName": "[traditional]", "disambiguation": "Special Purpose Artist", "url": "https://www.setlist.fm/setlists/traditional-5bd2f7e4.html"}}, {"name": "Dandelion Wine"}, {"name": "You Never Know"}, {"name": "Colorado"}, {"name": "Black Elk Speaks"}, {"name": "Spring-Heeled Jack"}, {"name": "Long Way to Go"}]}, {"encore": 1, "song": [{"name": "Let It Bleed", "cover": {"mbid": "b071f9fa-14b0-4217-8e97-eb41da73f598", "name": "The Rolling Stones", "sortName": "Rolling Stones, The", "disambiguation": "", "url": "https://www.setlist.fm/setlists/the-rolling-stones-bd6ad22.html"}}]}]}, "url": "https://www.setlist.fm/setlist/railroad-earth/2011/sherman-theater-stroudsburg-pa-73d90ec1.html"}, {"id": "7bf64274", "versionId": "23309017", "eventDate": "18-11-2011", "lastUpdated": "2020-03-18T20:46:22.000+0000", "artist": {"mbid": "b2e2abfa-fb1e-4be0-b500-56c4584f41cd", "name": "Railroad Earth", "sortName": "Railroad Earth", "disambiguation": "", "url": "https://www.setlist.fm/setlists/railroad-earth-2bd6d8c2.html"}, "venue": {"id": "1bd4cd18", "name": "Beachland Ballroom and Tavern", "city": {"id": "5150529", "name": "Cleveland", "state": "Ohio", "stateCode": "OH", "coords": {"lat": 41.4994954, "long": -81.6954088}, "country": {"code": "US", "name": "United States"}}, "url": "https://www.setlist.fm/venue/beachland-ballroom-and-tavern-cleveland-oh-usa-1bd4cd18.html"}, "sets": {"set": [{"song": [{"name": "Dandelion Wine"}, {"name": "The Good Life"}, {"name": "Bread and Water"}, {"name": "For Love", "cover": {"mbid": "c81d48a8-5c86-4160-b3d4-1275e7ba3212", "name": "Robert Earl Keen", "sortName": "Keen, Robert Earl", "disambiguation": "", "url": "https://www.setlist.fm/setlists/robert-earl-keen-2bd6287e.html"}}, {"name": "Mourning Flies"}, {"name": "Colorado"}, {"name": "The Hunting Song"}, {"name": "The New Lee Highway Blues", "cover": {"mbid": "00daff08-6cd1-4f91-b1ec-2f8ce8603442", "name": "David Bromberg", "sortName": "Bromberg, David", "disambiguation": "", "url": "https://www.setlist.fm/setlists/david-bromberg-2bd7a0ae.html"}}, {"name": "Goat"}, {"name": "Walk Beside Me", "cover": {"mbid": "07194211-0eda-43c4-8d04-0dbbc1f89674", "name": "Tim O\u2019Brien & Darrell Scott", "sortName": "O\u2019Brien, Tim & Scott, Darrell", "url": "https://www.setlist.fm/setlists/tim-obrien-and-darrell-scott-5bdae39c.html"}}, {"name": "Saddle of the Sun"}, {"name": "Seven Story Mountain"}, {"name": "Reuben's Train", "cover": {"mbid": "9be7f096-97ec-4615-8957-8d40b5dcbc41", "name": "[traditional]", "sortName": "[traditional]", "disambiguation": "Special Purpose Artist", "url": "https://www.setlist.fm/setlists/traditional-5bd2f7e4.html"}}, {"name": "Mountain Time"}, {"name": "Spring-Heeled Jack"}, {"name": "Elko"}, {"name": "Hard Livin'"}]}, {"encore": 1, "song": [{"name": "My Sisters and Brothers", "cover": {"mbid": "8102159a-bc0a-436e-a79c-3ef92b080b30", "name": "Charles Johnson", "sortName": "Johnson, Charles", "disambiguation": "Johnson Brothers", "url": "https://www.setlist.fm/setlists/charles-johnson-3dfd18b.html"}}]}]}, "url": "https://www.setlist.fm/setlist/railroad-earth/2011/beachland-ballroom-and-tavern-cleveland-oh-7bf64274.html"}, {"id": "23951ccf", "versionId": "3163d3f", "eventDate": "17-11-2011", "lastUpdated": "2019-02-07T20:20:58.000+0000", "artist": {"mbid": "b2e2abfa-fb1e-4be0-b500-56c4584f41cd", "name": "Railroad Earth", "sortName": "Railroad Earth", "disambiguation": "", "url": "https://www.setlist.fm/setlists/railroad-earth-2bd6d8c2.html"}, "venue": {"id": "2bd6d0be", "name": "Newport Music Hall", "city": {"id": "4509177", "name": "Columbus", "state": "Ohio", "stateCode": "OH", "coords": {"lat": 39.9611755, "long": -82.9987942}, "country": {"code": "US", "name": "United States"}}, "url": "https://www.setlist.fm/venue/newport-music-hall-columbus-oh-usa-2bd6d0be.html"}, "sets": {"set": []}, "url": "https://www.setlist.fm/setlist/railroad-earth/2011/newport-music-hall-columbus-oh-23951ccf.html"}, {"id": "bca859e", "versionId": "3b45ec94", "eventDate": "21-10-2011", "lastUpdated": "2017-08-25T02:17:13.000+0000", "artist": {"mbid": "b2e2abfa-fb1e-4be0-b500-56c4584f41cd", "name": "Railroad Earth", "sortName": "Railroad Earth", "disambiguation": "", "url": "https://www.setlist.fm/setlists/railroad-earth-2bd6d8c2.html"}, "venue": {"id": "13d60ddd", "name": "The Fillmore", "city": {"id": "4460243", "name": "Charlotte", "state": "North Carolina", "stateCode": "NC", "coords": {"lat": 35.2270869, "long": -80.8431268}, "country": {"code": "US", "name": "United States"}}, "url": "https://www.setlist.fm/venue/the-fillmore-charlotte-nc-usa-13d60ddd.html"}, "sets": {"set": []}, "url": "https://www.setlist.fm/setlist/railroad-earth/2011/the-fillmore-charlotte-nc-bca859e.html"}]}